azure/mgmt/resourcemover/__init__.py
azure/mgmt/resourcemover/_configuration.py
azure/mgmt/resourcemover/_patch.py
azure/mgmt/resourcemover/_resource_mover_service_api.py
azure/mgmt/resourcemover/_serialization.py
azure/mgmt/resourcemover/_vendor.py
azure/mgmt/resourcemover/_version.py
azure/mgmt/resourcemover/py.typed
azure/mgmt/resourcemover/aio/__init__.py
azure/mgmt/resourcemover/aio/_configuration.py
azure/mgmt/resourcemover/aio/_patch.py
azure/mgmt/resourcemover/aio/_resource_mover_service_api.py
azure/mgmt/resourcemover/aio/operations/__init__.py
azure/mgmt/resourcemover/aio/operations/_move_collections_operations.py
azure/mgmt/resourcemover/aio/operations/_move_resources_operations.py
azure/mgmt/resourcemover/aio/operations/_operations_discovery_operations.py
azure/mgmt/resourcemover/aio/operations/_patch.py
azure/mgmt/resourcemover/aio/operations/_unresolved_dependencies_operations.py
azure/mgmt/resourcemover/models/__init__.py
azure/mgmt/resourcemover/models/_models_py3.py
azure/mgmt/resourcemover/models/_patch.py
azure/mgmt/resourcemover/models/_resource_mover_service_api_enums.py
azure/mgmt/resourcemover/operations/__init__.py
azure/mgmt/resourcemover/operations/_move_collections_operations.py
azure/mgmt/resourcemover/operations/_move_resources_operations.py
azure/mgmt/resourcemover/operations/_operations_discovery_operations.py
azure/mgmt/resourcemover/operations/_patch.py
azure/mgmt/resourcemover/operations/_unresolved_dependencies_operations.py
azure_mgmt_resourcemover-1.1.0.dist-info/LICENSE
azure_mgmt_resourcemover-1.1.0.dist-info/METADATA
azure_mgmt_resourcemover-1.1.0.dist-info/WHEEL
azure_mgmt_resourcemover-1.1.0.dist-info/top_level.txt
azure_mgmt_resourcemover-1.1.0.dist-info/RECORD
